[{"name":"Test Prediction","description":"Adding a Prediction to the Developer Account","probability":5,"expiry":"2020-12-08","outcome":null},{"name":"Hello","description":"Myb asdfsadf","probability":5,"expiry":"2020-12-09","outcome":null},{"name":"Random Pred","description":"dsafasewafasdf","probability":90,"expiry":"2020-12-22","outcome":null},{"name":"Hallo DU hurensohn","description":"dsafasef","probability":5,"expiry":"2018-10-17","outcome":null},{"name":"fasdfawefawef","description":"adsfawefasf","probability":50,"expiry":"2020-12-14","outcome":null}]